easyeda/__init__.py
easyeda/core/__init__.py
easyeda/core/canvas.py
easyeda/core/layers.py
easyeda/core/pcb.py
easyeda_python_sdk-0.1.0.dist-info/WHEEL
easyeda_python_sdk-0.1.0.dist-info/METADATA
easyeda_python_sdk-0.1.0.dist-info/RECORD
