Metadata-Version: 2.1
Name: easyeda-python-sdk
Version: 0.1.0
Summary: Python SDK for easyeda
License: MIT
Author: Thomas Mahé
Author-email: contact@tmahe.dev
Requires-Python: >=3.10,<4.0
Classifier: License :: OSI Approved :: MIT License
Classifier: Programming Language :: Python :: 3
Classifier: Programming Language :: Python :: 3.10
Classifier: Programming Language :: Python :: 3.11
